.bandit
.git_archival.txt
.gitattributes
.gitignore
.pre-commit-config.yaml
LICENSE.txt
README.md
pyproject.toml
setup.cfg
.github/dependabot.yml
.github/workflows/ci.yaml
.github/workflows/deploy-sdist.yaml
continuous_integration/environment.yaml
examples/aws_abi_l1b_20220101_18.yaml
examples/local_abi_l1b.yaml
intake_satpy/__init__.py
intake_satpy/generic.py
intake_satpy/version.py
intake_satpy.egg-info/PKG-INFO
intake_satpy.egg-info/SOURCES.txt
intake_satpy.egg-info/dependency_links.txt
intake_satpy.egg-info/entry_points.txt
intake_satpy.egg-info/requires.txt
intake_satpy.egg-info/top_level.txt
intake_satpy/tests/__init__.py
intake_satpy/tests/test_driver.py