Metadata-Version: 2.1
Name: intake-satpy
Version: 0.1.0.post0
Summary: Intake drivers using Satpy to read and manipulate data
License: GPLv3
Keywords: intake,pytroll,satpy
Classifier: Programming Language :: Python :: 3
Classifier: Development Status :: 3 - Alpha
Classifier: Intended Audience :: Science/Research
Classifier: License :: OSI Approved :: GNU General Public License v3 or later (GPLv3+)
Classifier: Operating System :: OS Independent
Classifier: Programming Language :: Python
Classifier: Topic :: Scientific/Engineering
Requires-Python: >=3.8
License-File: LICENSE.txt
Requires-Dist: intake
Requires-Dist: intake-xarray
Requires-Dist: satpy
Provides-Extra: tests
Requires-Dist: pytest; extra == "tests"
